MovieRecEngine/__init__.py
MovieRecEngine/__main__.py
MovieRecEngine-0.1.1.dist-info/LICENSE
MovieRecEngine-0.1.1.dist-info/METADATA
MovieRecEngine-0.1.1.dist-info/WHEEL
MovieRecEngine-0.1.1.dist-info/top_level.txt
MovieRecEngine-0.1.1.dist-info/RECORD
