Metadata-Version: 2.1
Name: MovieRecEngine
Version: 0.1.1
Summary: MovieRecEngine is a simple collaborative filtering based library using Pytorch Sequential Neural Network to make prediction of user ratings for an unseen movie based on his/her past interests/ratings provided.
Home-page: https://github.com/MrR0b0t-23/MovieRecEngine
Author: Ashwin
Author-email: imashwin02@gmail.com
License: UNKNOWN
Project-URL: Bug Tracker, https://github.com/MrR0b0t-23/MovieRecEngine/issues
Keywords: Movie Recommendation Engine,Deep Learning,Movie Recommendation System,Collabative Filtering,Recommendation,MovieRecEngine,Pytorch Recommendation
Platform: UNKNOWN
Classifier: Development Status :: 5 - Production/Stable
Classifier: Programming Language :: Python :: 3
Classifier: License :: OSI Approved :: MIT License
Classifier: Operating System :: OS Independent
Requires-Python: >=3.6
Requires-Dist: torch (>=1.6.0)
Requires-Dist: tez (>=0.1.2)
Requires-Dist: pandas (>=1.2.2)
